Metadata-Version: 2.1
Name: opaivipul
Version: 1.14.1
Summary: The official Python library for the openai API
Home-page: 
Author: vipul dholariya
Author-email: OpenAI <support@openai.com>
License: Apache License
Project-URL: Homepage, https://github.com/openai/openai-python
Project-URL: Repository, https://github.com/openai/openai-python
Classifier: Typing :: Typed
Classifier: Intended Audience :: Developers
Classifier: Programming Language :: Python :: 3.7
Classifier: Programming Language :: Python :: 3.8
Classifier: Programming Language :: Python :: 3.9
Classifier: Programming Language :: Python :: 3.10
Classifier: Programming Language :: Python :: 3.11
Classifier: Programming Language :: Python :: 3.12
Classifier: Operating System :: OS Independent
Classifier: Operating System :: POSIX
Classifier: Operating System :: MacOS
Classifier: Operating System :: POSIX :: Linux
Classifier: Operating System :: Microsoft :: Windows
Classifier: Topic :: Software Development :: Libraries :: Python Modules
Classifier: License :: OSI Approved :: Apache Software License
Requires-Python: >=3.10
License-File: LICENSE
Requires-Dist: httpx <1,>=0.23.0
Requires-Dist: pydantic <3,>=1.9.0
Requires-Dist: typing-extensions <5,>=4.7
Requires-Dist: anyio <5,>=3.5.0
Requires-Dist: distro <2,>=1.7.0
Requires-Dist: sniffio
Requires-Dist: tqdm >4
Requires-Dist: cached-property ; python_version < "3.8"
Provides-Extra: datalib
Requires-Dist: numpy >=1 ; extra == 'datalib'
Requires-Dist: pandas >=1.2.3 ; extra == 'datalib'
Requires-Dist: pandas-stubs >=1.1.0.11 ; extra == 'datalib'
Provides-Extra: dev
Requires-Dist: pytest >=7.0 ; extra == 'dev'
Requires-Dist: twine >=4.0.2 ; extra == 'dev'
